ezRay/__init__.py
ezRay/ezRay.py
ezRay/listener.py
ezRay/scheduler.py
ezray-1.1.8.dist-info/LICENSE
ezray-1.1.8.dist-info/METADATA
ezray-1.1.8.dist-info/WHEEL
ezray-1.1.8.dist-info/RECORD
