Metadata-Version: 2.1
Name: ezRay
Version: 1.1.8
Summary: A simple implementation of the ray framework for method agnostic task paralellization.
License: GNU GPLv3
Author: Bela Vogler
Author-email: bela.vogler@uni-jena.de
Requires-Python: >=3.10,<4.0
Classifier: License :: Other/Proprietary License
Classifier: Programming Language :: Python :: 3
Classifier: Programming Language :: Python :: 3.10
Classifier: Programming Language :: Python :: 3.11
Classifier: Programming Language :: Python :: 3.12
Classifier: Programming Language :: Python :: 3.13
Requires-Dist: ipython (>=8.32.0,<9.0.0)
Requires-Dist: psutil (>=6.1.1,<7.0.0)
Requires-Dist: ray[default] (>=2.42.1,<3.0.0)
Requires-Dist: tqdm (>=4.67.1,<5.0.0)
